jeng/__init__.py
jeng/exception.py
jeng/generate.py
jeng/jeng.py
jeng/model.py
jeng/parse.py
jeng/xml/WMLS.WSDL
jeng-1.0.1.dist-info/licenses/license.md
jeng-1.0.1.dist-info/METADATA
jeng-1.0.1.dist-info/WHEEL
jeng-1.0.1.dist-info/top_level.txt
jeng-1.0.1.dist-info/RECORD
