Metadata-Version: 2.4
Name: jeng
Version: 1.0.1
Summary: A simple WITSML client with utilities.
Home-page: https://github.com/nazebzurati/jeng
Author: Nazeb Zurati
Author-email: nazeb04@gmail.com
License: MIT
Keywords: python,witsml,soap-client,pandas
Classifier: License :: OSI Approved :: MIT License
Classifier: Programming Language :: Python :: 3
Classifier: Operating System :: OS Independent
License-File: license.md
Requires-Dist: zeep>=4.3.1
Requires-Dist: xmltodict>=0.14.0
Requires-Dist: pandas>=2.2.3
Provides-Extra: dev
Requires-Dist: pytest>=8.3.5; extra == "dev"
Requires-Dist: pytest-dependency>=0.6.0; extra == "dev"
Requires-Dist: pytest-env>=1.1.5; extra == "dev"
Requires-Dist: black>=25.1.0; extra == "dev"
Requires-Dist: isort>=6.0.1; extra == "dev"
Requires-Dist: check-manifest>=0.50; extra == "dev"
Requires-Dist: twine>=6.1.0; extra == "dev"
Requires-Dist: coverage>=7.8.0; extra == "dev"
Dynamic: author
Dynamic: author-email
Dynamic: classifier
Dynamic: description
Dynamic: description-content-type
Dynamic: home-page
Dynamic: keywords
Dynamic: license
Dynamic: license-file
Dynamic: provides-extra
Dynamic: requires-dist
Dynamic: summary
